{
  "version": "6.3.1",
  "flags": {},
  "shapes": [
    {
      "label": "road",
      "points": [
        [
          171.9230769230769,
          378.1868131868132
        ],
        [
          640.0,
          99.85602598336237
        ],
        [
          640.0,
          405.65934065934067
        ],
        [
          174.6195652173913,
          378.3152173913043
        ],
        [
          173.5326086956522,
          376.14130434782606
        ],
        [
          120.82417582417581,
          350.16483516483515
        ],
        [
          125.76923076923076,
          357.85714285714283
        ],
        [
          139.50549450549448,
          357.85714285714283
        ],
        [
          148.8461538461538,
          361.7032967032967
        ],
        [
          161.48351648351644,
          372.1428571428571
        ]
      ],
      "group_id": null,
      "description": "",
      "shape_type": "polygon",
      "flags": {},
      "mask": null
    },
    {
      "label": "lane",
      "points": [
        [
          173.021978021978,
          377.6373626373626
        ],
        [
          640.0,
          98.97448705141016
        ],
        [
          640.0,
          90.82417582417582
        ],
        [
          177.41758241758242,
          343.57142857142856
        ],
        [
          161.48351648351644,
          342.4725274725275
        ],
        [
          146.64835164835165,
          333.13186813186815
        ],
        [
          139.50549450549448,
          324.34065934065933
        ],
        [
          96.09890109890107,
          300.16483516483515
        ],
        [
          0.0,
          250.236355822948
        ],
        [
          0.0,
          272.3369565217391
        ],
        [
          121.92307692307689,
          352.9120879120879
        ],
        [
          126.3186813186813,
          358.4065934065934
        ],
        [
          140.60439560439556,
          357.85714285714283
        ],
        [
          156.5384615384615,
          371.04395604395603
        ]
      ],
      "group_id": null,
      "description": "",
      "shape_type": "polygon",
      "flags": {},
      "mask": null
    }
  ],
  "imagePath": "road_1784024816158.jpg",
  "imageData": null,
  "imageHeight": 480,
  "imageWidth": 640
}